puya/ARCHITECTURE.md
puya/__init__.py
puya/__main__.py
puya/_typeshed/README.md
puya/_typeshed/stdlib/VERSIONS
puya/_typeshed/stdlib/_collections_abc.pyi
puya/_typeshed/stdlib/_typeshed/__init__.pyi
puya/_typeshed/stdlib/abc.pyi
puya/_typeshed/stdlib/builtins.pyi
puya/_typeshed/stdlib/collections/__init__.pyi
puya/_typeshed/stdlib/collections/abc.pyi
puya/_typeshed/stdlib/sys.pyi
puya/_typeshed/stdlib/types.pyi
puya/_typeshed/stdlib/typing.pyi
puya/_typeshed/stdlib/typing_extensions.pyi
puya/_typeshed/stubs/mypy-extensions/mypy_extensions.pyi
puya/_vendor/mypy/.version
puya/_vendor/mypy/__init__.py
puya/_vendor/mypy/__main__.py
puya/_vendor/mypy/api.py
puya/_vendor/mypy/applytype.py
puya/_vendor/mypy/argmap.py
puya/_vendor/mypy/binder.py
puya/_vendor/mypy/bogus_type.py
puya/_vendor/mypy/build.py
puya/_vendor/mypy/checker.py
puya/_vendor/mypy/checkexpr.py
puya/_vendor/mypy/checkmember.py
puya/_vendor/mypy/checkpattern.py
puya/_vendor/mypy/checkstrformat.py
puya/_vendor/mypy/config_parser.py
puya/_vendor/mypy/constant_fold.py
puya/_vendor/mypy/constraints.py
puya/_vendor/mypy/copytype.py
puya/_vendor/mypy/defaults.py
puya/_vendor/mypy/dmypy/__init__.py
puya/_vendor/mypy/dmypy/__main__.py
puya/_vendor/mypy/dmypy/client.py
puya/_vendor/mypy/dmypy_os.py
puya/_vendor/mypy/dmypy_server.py
puya/_vendor/mypy/dmypy_util.py
puya/_vendor/mypy/erasetype.py
puya/_vendor/mypy/errorcodes.py
puya/_vendor/mypy/errors.py
puya/_vendor/mypy/evalexpr.py
puya/_vendor/mypy/expandtype.py
puya/_vendor/mypy/exprtotype.py
puya/_vendor/mypy/fastparse.py
puya/_vendor/mypy/find_sources.py
puya/_vendor/mypy/fixup.py
puya/_vendor/mypy/freetree.py
puya/_vendor/mypy/fscache.py
puya/_vendor/mypy/fswatcher.py
puya/_vendor/mypy/gclogger.py
puya/_vendor/mypy/git.py
puya/_vendor/mypy/graph_utils.py
puya/_vendor/mypy/indirection.py
puya/_vendor/mypy/infer.py
puya/_vendor/mypy/inspections.py
puya/_vendor/mypy/ipc.py
puya/_vendor/mypy/join.py
puya/_vendor/mypy/literals.py
puya/_vendor/mypy/lookup.py
puya-0.6.0.dist-info/LICENSE
puya-0.6.0.dist-info/METADATA
puya-0.6.0.dist-info/WHEEL
puya-0.6.0.dist-info/entry_points.txt
puya-0.6.0.dist-info/RECORD
