Metadata-Version: 2.1
Name: puya
Version: 0.6.0
Summary: An optimising Python to TEAL compiler
Author: Algorand Foundation
Author-email: contact@algorand.foundation
Requires-Python: >=3.12,<4.0
Classifier: Development Status :: 3 - Alpha
Classifier: Intended Audience :: Developers
Classifier: Programming Language :: Python :: 3
Classifier: Programming Language :: Python :: 3.12
Classifier: Topic :: Software Development :: Compilers
Requires-Dist: attrs (>=23.1.0,<24.0.0)
Requires-Dist: docstring-parser (>=0.14.1)
Requires-Dist: immutabledict (>=4.0.0,<5.0.0)
Requires-Dist: mypy_extensions (>=1.0.0,<2.0.0)
Requires-Dist: networkx (>=3.1,<4.0)
Requires-Dist: pycryptodomex (>=3.6.0,<4)
Requires-Dist: structlog (>=23.2.0,<24.0.0)
Requires-Dist: typing-extensions (>=4.8.0,<5.0.0)
